{
  "Type": "AthenaBackpackItemDefinition",
  "Name": "Backpack_SnowyPeas",
  "Class": "UScriptClass'AthenaBackpackItemDefinition'",
  "Flags": "RF_Public | RF_Standalone | RF_Transactional | RF_WasLoaded | RF_LoadCompleted",
  "Properties": {
    "CharacterParts": [
      {
        "ObjectName": "CustomCharacterPart'CP_Backpack_SnowyPeas'",
        "ObjectPath": "/BRCosmetics/Characters/CharacterParts/Backpacks/CP_Backpack_SnowyPeas.1"
      }
    ],
    "ShotGridIds": [
      168482
    ],
    "BaseShotGridId": 168482,
    "Rarity": "EFortRarity::Rare",
    "ItemName": {
      "Namespace": "",
      "Key": "719A0E33484BBACA06F207AAF51A5781",
      "SourceString": "Emergency Carrot",
      "LocalizedString": "Emergency Carrot"
    },
    "ItemDescription": {
      "Namespace": "",
      "Key": "070AEEFB457670CDCCFA21B4F2CEBB85",
      "SourceString": "The nose knows.",
      "LocalizedString": "The nose knows."
    },
    "ItemShortDescription": {
      "Namespace": "",
      "Key": "3BF20849479CCDEB4BCC70AEF5183264",
      "SourceString": "Back Bling",
      "LocalizedString": "Back Bling"
    },
    "DataList": [
      {
        "MinLevel": 1,
        "MaxLevel": 1
      },
      {
        "Icon": {
          "AssetPathName": "/BRCosmetics/UI/Foundation/Textures/Icons/Backpacks/S39/T_Icon_Backpacks_SnowyPeas.T_Icon_Backpacks_SnowyPeas",
          "SubPathString": ""
        }
      },
      {
        "LargeIcon": {
          "AssetPathName": "/BRCosmetics/UI/Foundation/Textures/Icons/Backpacks/S39/T_Icon_Backpacks_SnowyPeas_L.T_Icon_Backpacks_SnowyPeas_L",
          "SubPathString": ""
        }
      },
      {
        "Tags": [
          "Cosmetics.Source.ItemShop",
          "Cosmetics.Filter.Season.39",
          "Cosmetics.Set.HumanMelt"
        ]
      },
      {
        "Traits": [
          "Item.Trait.SingleStack"
        ]
      },
      {
        "GeneratedTagsIndexes": [
          270,
          359,
          248,
          603,
          246,
          332,
          835,
          222,
          52,
          943,
          1042,
          444,
          1181,
          309,
          1333,
          1357,
          93,
          664,
          1556,
          1698,
          2344,
          2420,
          2421,
          2637,
          283,
          378,
          2712,
          3843,
          6626,
          5127,
          7876
        ]
      }
    ]
  }
}