{
  "Type": "AthenaCharacterItemDefinition",
  "Name": "Bean_Viper",
  "Class": "UScriptClass'AthenaCharacterItemDefinition'",
  "Flags": "RF_Public | RF_Standalone | RF_Transactional | RF_WasLoaded | RF_LoadCompleted",
  "Properties": {
    "BaseCharacterParts": [
      {
        "AssetPathName": "/BeanstalkCosmetics/Cosmetics/Head/CP_Bean_Head_Hood.CP_Bean_Head_Hood",
        "SubPathString": ""
      },
      {
        "AssetPathName": "/BeanstalkCosmetics/Cosmetics/Body/CP_Bean_Body_Fantasy.CP_Bean_Body_Fantasy",
        "SubPathString": ""
      }
    ],
    "Gender": "EFortCustomGender::Female",
    "AdditionalDataFields": [
      {
        "ObjectName": "BeanCosmeticItemDefinitionBase'Bean_Viper:BeanCosmeticItemDefinitionBase_1'",
        "ObjectPath": "/BeanstalkCosmetics/Cosmetics/Def/CID/Bean_Viper.1"
      }
    ],
    "ItemName": {
      "Namespace": "",
      "Key": "F624333F437519B805437B98AF2F790C",
      "SourceString": "Fusion",
      "LocalizedString": "Fusion"
    },
    "ItemDescription": {
      "Namespace": "",
      "Key": "82F1B9BF486A723F4F14709BC99F0DB6",
      "SourceString": "Merged into one.",
      "LocalizedString": "Merged into one."
    },
    "ItemShortDescription": {
      "Namespace": "",
      "Key": "9658361F4EFF6B98FF153898E58C9D52",
      "SourceString": "Outfit",
      "LocalizedString": "Outfit"
    },
    "DataList": [
      {
        "Icon": {
          "AssetPathName": "/BeanstalkCosmetics/Cosmetics/Icons/T_Bean_Viper.T_Bean_Viper",
          "SubPathString": ""
        }
      },
      {
        "LargeIcon": {
          "AssetPathName": "/BeanstalkCosmetics/Cosmetics/Icons/T_Bean_Viper_L.T_Bean_Viper_L",
          "SubPathString": ""
        }
      },
      {
        "MinLevel": 1,
        "MaxLevel": 1
      },
      {
        "Tags": [
          "Beanstalk.Cosmetics.Character",
          "Cosmetics.Set.Nothingness",
          "Cosmetics.Filter.Season.11",
          "Phoebe.Cosmetic.Minus.Zone1"
        ]
      },
      {
        "Traits": [
          "Item.Trait.Transient",
          "Item.Trait.SingleStack"
        ]
      }
    ]
  }
}