{
  "Type": "AthenaCharacterItemDefinition",
  "Name": "Bean_GreenJacketFNCS",
  "Class": "UScriptClass'AthenaCharacterItemDefinition'",
  "Flags": "RF_Public | RF_Standalone | RF_Transactional | RF_WasLoaded | RF_LoadCompleted",
  "Properties": {
    "BaseCharacterParts": [
      {
        "AssetPathName": "/BeanstalkCosmetics/Cosmetics/Head/CP_Bean_Head_HairUpdo.CP_Bean_Head_HairUpdo",
        "SubPathString": ""
      },
      {
        "AssetPathName": "/BeanstalkCosmetics/Cosmetics/Body/CP_Bean_Body_Sport.CP_Bean_Body_Sport",
        "SubPathString": ""
      }
    ],
    "Gender": "EFortCustomGender::Female",
    "AdditionalDataFields": [
      {
        "ObjectName": "BeanCosmeticItemDefinitionBase'Bean_GreenJacketFNCS:BeanCosmeticItemDefinitionBase_1'",
        "ObjectPath": "/BeanstalkCosmetics/Cosmetics/Def/CID/Bean_GreenJacketFNCS.1"
      }
    ],
    "ItemName": {
      "Namespace": "",
      "Key": "2C39DB8B465F5CA0A41A8F8F5B012B3E",
      "SourceString": "Champion Kyra",
      "LocalizedString": "Champion Kyra"
    },
    "ItemDescription": {
      "Namespace": "",
      "Key": "E135BF9C41B4AF80C10893AD6612A9A3",
      "SourceString": "Never afraid to secure the crown.",
      "LocalizedString": "Never afraid to secure the crown."
    },
    "ItemShortDescription": {
      "Namespace": "",
      "Key": "9658361F4EFF6B98FF153898E58C9D52",
      "SourceString": "Outfit",
      "LocalizedString": "Outfit"
    },
    "DataList": [
      {
        "Icon": {
          "AssetPathName": "/BeanstalkCosmetics/Cosmetics/Icons/T_Bean_GreenJacketFNCS.T_Bean_GreenJacketFNCS",
          "SubPathString": ""
        }
      },
      {
        "LargeIcon": {
          "AssetPathName": "/BeanstalkCosmetics/Cosmetics/Icons/T_Bean_GreenJacketFNCS_L.T_Bean_GreenJacketFNCS_L",
          "SubPathString": ""
        }
      },
      {
        "MinLevel": 1,
        "MaxLevel": 1
      },
      {
        "Tags": [
          "Beanstalk.Cosmetics.Character",
          "Cosmetics.Filter.Season.26",
          "Cosmetics.Set.FNCS",
          "Phoebe.Cosmetic.Minus.Zone1"
        ]
      },
      {
        "Traits": [
          "Item.Trait.Transient",
          "Item.Trait.SingleStack"
        ]
      }
    ]
  }
}