{
  "Type": "AthenaBackpackItemDefinition",
  "Name": "BID_Ninja_010",
  "Class": "UScriptClass'AthenaBackpackItemDefinition'",
  "Flags": "RF_Public | RF_Standalone | RF_Transactional | RF_WasLoaded | RF_LoadCompleted",
  "Properties": {
    "CharacterParts": [
      {
        "ObjectName": "CustomCharacterPart'Male_Ninja_05'",
        "ObjectPath": "/SaveTheWorld/Characters/CharacterParts/Backpacks/Male_Ninja_05.1"
      }
    ],
    "ItemVariants": [
      {
        "ObjectName": "FortCosmeticCharacterPartVariant'BID_Ninja_010:Male_Ninja_05'",
        "ObjectPath": "/SaveTheWorld/Items/Cosmetics/Backpacks/Ninja/BID_Ninja_010.1"
      }
    ],
    "bIsOwnedByCampaignHero": true,
    "Rarity": "EFortRarity::Epic",
    "DataList": [
      {
        "MinLevel": 1,
        "MaxLevel": 1
      },
      {
        "Icon": {
          "AssetPathName": "/SaveTheWorld/UI/Foundation/Textures/Icons/Backpacks/T-Icon-Backpacks-Ninja-010-VariantEpic.T-Icon-Backpacks-Ninja-010-VariantEpic",
          "SubPathString": ""
        }
      },
      {
        "LargeIcon": {
          "AssetPathName": "/SaveTheWorld/UI/Foundation/Textures/Icons/Backpacks/T-Icon-Backpacks-Ninja-010-VariantEpic-L.T-Icon-Backpacks-Ninja-010-VariantEpic-L",
          "SubPathString": ""
        }
      },
      {
        "Tags": [
          "Cosmetics.UserFacingFlags.HasVariants",
          "Cosmetics.Source.CampaignHero"
        ]
      },
      {
        "Traits": [
          "Item.Trait.Transient",
          "Item.Trait.SingleStack"
        ]
      }
    ]
  }
}