{
  "Type": "AthenaCharacterItemDefinition",
  "Name": "CID_064_Athena_Commando_F_SkiGirl_GBR",
  "Class": "UScriptClass'AthenaCharacterItemDefinition'",
  "Flags": "RF_Public | RF_Standalone | RF_Transactional | RF_WasLoaded | RF_LoadCompleted",
  "Properties": {
    "BaseCharacterParts": [
      {
        "AssetPathName": "/BRCosmetics/Characters/CharacterParts/Female/Medium/Bodies/F_Med_Soldier_BR42_GBR.F_Med_Soldier_BR42_GBR",
        "SubPathString": ""
      },
      {
        "AssetPathName": "/BRCosmetics/Athena/Heroes/Meshes/Heads/F_Med_Soldier_SkiMask_01_ATH_GBR.F_Med_Soldier_SkiMask_01_ATH_GBR",
        "SubPathString": ""
      }
    ],
    "Gender": "EFortCustomGender::Female",
    "DefaultMontageLookupTable": {
      "AssetPathName": "/Game/Animation/Game/MainPlayer/Menu/MontageLookUpTables/MediumFemale.MediumFemale",
      "SubPathString": ""
    },
    "ItemVariants": [
      {
        "ObjectName": "FortCosmeticPropertyVariant'CID_064_Athena_Commando_F_SkiGirl_GBR:FortCosmeticPropertyVariant_0'",
        "ObjectPath": "/BRCosmetics/Athena/Items/Cosmetics/Characters/CID_064_Athena_Commando_F_SkiGirl_GBR.1"
      }
    ],
    "ShotGridIds": [
      17841
    ],
    "BaseShotGridId": 17841,
    "Rarity": "EFortRarity::Epic",
    "ItemName": {
      "Namespace": "",
      "Key": "B3371FEB49EAD8F62879C8A9703FD432",
      "SourceString": "Mogul Master (GBR)",
      "LocalizedString": "Mogul Master (GBR)"
    },
    "ItemDescription": {
      "Namespace": "",
      "Key": "8127882F4F6B26CD3BA355A8D0A4C2B8",
      "SourceString": "Carve through the competition.",
      "LocalizedString": "Carve through the competition."
    },
    "ItemShortDescription": {
      "Namespace": "",
      "Key": "EBE0ACB646CEC4DA35CC17BACBA3652F",
      "SourceString": "Outfit",
      "LocalizedString": "Outfit"
    },
    "DataList": [
      {
        "LargeIcon": {
          "AssetPathName": "/BRCosmetics/UI/Foundation/Textures/Icons/Heroes/Athena/Soldier/T-Soldier-HID-064-Athena-Commando-F-SkiGirl-GBR-L.T-Soldier-HID-064-Athena-Commando-F-SkiGirl-GBR-L",
          "SubPathString": ""
        }
      },
      {
        "Icon": {
          "AssetPathName": "/BRCosmetics/UI/Foundation/Textures/Icons/Heroes/Athena/Soldier/T-Soldier-HID-064-Athena-Commando-F-SkiGirl-GBR.T-Soldier-HID-064-Athena-Commando-F-SkiGirl-GBR",
          "SubPathString": ""
        }
      },
      {
        "MinLevel": 1,
        "MaxLevel": 1
      },
      {
        "Tags": [
          "Cosmetics.Source.ItemShop",
          "Cosmetics.Set.WinterSki",
          "Phoebe.Cosmetic.Minus.Zone2",
          "Cosmetics.Filter.Season.2",
          "Cosmetics.Filter.Event.WinterOlympics2018",
          "SoundLibrary.ID.StepType.BootsCombat",
          "SoundLibrary.ID.HandType.Glove",
          "SoundLibrary.ID.ClothingType.GearTactical",
          "Cosmetics.Gating.Allow.Shoes"
        ]
      },
      {
        "Traits": [
          "Item.Trait.SingleStack"
        ]
      },
      {
        "GeneratedTagsIndexes": [
          547,
          611,
          359,
          551,
          247,
          248,
          603,
          7,
          85,
          515,
          26,
          531,
          532,
          533,
          45,
          246,
          44,
          782,
          1248,
          52,
          948,
          8053,
          697,
          127,
          996,
          998,
          938,
          939,
          940,
          1418,
          1419,
          1620,
          70,
          347,
          183,
          1630
        ]
      }
    ]
  }
}