{
  "Type": "AthenaCharacterItemDefinition",
  "Name": "CID_A_289_Athena_Commando_M_Gumball",
  "Class": "UScriptClass'AthenaCharacterItemDefinition'",
  "Flags": "RF_Public | RF_Standalone | RF_Transactional | RF_WasLoaded | RF_LoadCompleted",
  "Properties": {
    "BaseCharacterParts": [
      {
        "AssetPathName": "/BRCosmetics/Characters/CharacterParts/Male/Medium/Heads/CP_Athena_Head_M_Gumball.CP_Athena_Head_M_Gumball",
        "SubPathString": ""
      },
      {
        "AssetPathName": "/BRCosmetics/Athena/Heroes/Meshes/Bodies/CP_Athena_Body_M_Gumball.CP_Athena_Body_M_Gumball",
        "SubPathString": ""
      },
      {
        "AssetPathName": "/BRCosmetics/Characters/CharacterParts/FaceAccessories/CP_M_MED_Gumball_FaceAcc.CP_M_MED_Gumball_FaceAcc",
        "SubPathString": ""
      }
    ],
    "Gender": "EFortCustomGender::Male",
    "FrontendAnimMontageIdleOverride": {
      "AssetPathName": "/BRCosmetics/Animation/Game/MainPlayer/Menu/BR/CustomSkins/_s19/GumballM/GumballM_Male_Idle_Montage.GumballM_Male_Idle_Montage",
      "SubPathString": ""
    },
    "BuiltInEmotes": [
      {
        "ObjectName": "AthenaDanceItemDefinition'EID_Gumball'",
        "ObjectPath": "/BRCosmetics/Athena/Items/Cosmetics/Dances/EID_Gumball.0"
      }
    ],
    "ItemVariants": [
      {
        "ObjectName": "FortCosmeticCharacterPartVariant'CID_A_289_Athena_Commando_M_Gumball:FortCosmeticCharacterPartVariant_0'",
        "ObjectPath": "/BRCosmetics/Athena/Items/Cosmetics/Characters/CID_A_289_Athena_Commando_M_Gumball.1"
      },
      {
        "ObjectName": "FortCosmeticPropertyVariant'CID_A_289_Athena_Commando_M_Gumball:FortCosmeticPropertyVariant_0'",
        "ObjectPath": "/BRCosmetics/Athena/Items/Cosmetics/Characters/CID_A_289_Athena_Commando_M_Gumball.2"
      }
    ],
    "VariantShotGridIds": [
      52330,
      52331
    ],
    "ShotGridIds": [
      50679,
      52330,
      52331
    ],
    "BaseShotGridId": 50679,
    "Rarity": "EFortRarity::Epic",
    "ItemName": {
      "Namespace": "",
      "Key": "24690F9643CA265E8C7A8D808C2DE92E",
      "SourceString": "Gumbo",
      "LocalizedString": "Gumbo"
    },
    "ItemDescription": {
      "Namespace": "",
      "Key": "DDC41F664811FDB60251399E90683052",
      "SourceString": "Synthetic flavors, authentic attitude.",
      "LocalizedString": "Synthetic flavors, authentic attitude."
    },
    "ItemShortDescription": {
      "Namespace": "",
      "Key": "9658361F4EFF6B98FF153898E58C9D52",
      "SourceString": "Outfit",
      "LocalizedString": "Outfit"
    },
    "DataList": [
      {
        "LargeIcon": {
          "AssetPathName": "/BRCosmetics/UI/Foundation/Textures/Icons/Heroes/Athena/Soldier/T-Soldier-HID-A-289-Athena-Commando-M-Gumball-L.T-Soldier-HID-A-289-Athena-Commando-M-Gumball-L",
          "SubPathString": ""
        }
      },
      {
        "Icon": {
          "AssetPathName": "/BRCosmetics/UI/Foundation/Textures/Icons/Heroes/Athena/Soldier/T-Soldier-HID-A-289-Athena-Commando-M-Gumball.T-Soldier-HID-A-289-Athena-Commando-M-Gumball",
          "SubPathString": ""
        }
      },
      {
        "MinLevel": 1,
        "MaxLevel": 1
      },
      {
        "Tags": [
          "Cosmetics.UserFacingFlags.HasUpgradeQuests",
          "Cosmetics.UserFacingFlags.BuiltInEmote",
          "Cosmetics.Source.Season19.BattlePass.Paid",
          "Cosmetics.Set.ChompSelf",
          "SoundLibrary.ID.StepType.BootsCombat",
          "SoundLibrary.ID.ClothingType.Generic",
          "SoundLibrary.ID.HandType.Glove",
          "Cosmetics.Filter.Season.19",
          "Cosmetics.Gating.Allow.Shoes"
        ]
      },
      {
        "Traits": [
          "Item.Trait.SingleStack"
        ]
      },
      {
        "GeneratedTagsIndexes": [
          539,
          546,
          548,
          556,
          162,
          249,
          563,
          573,
          126,
          122,
          170,
          244,
          603,
          567,
          53,
          641,
          642,
          246,
          787,
          985,
          487,
          89,
          1972
        ]
      }
    ]
  }
}