{
  "Type": "AthenaCharacterItemDefinition",
  "Name": "CID_026_Athena_Commando_M",
  "Class": "UScriptClass'AthenaCharacterItemDefinition'",
  "Flags": "RF_Public | RF_Standalone | RF_Transactional | RF_WasLoaded | RF_LoadCompleted",
  "Properties": {
    "BaseCharacterParts": [
      {
        "AssetPathName": "/Game/Athena/Heroes/Meshes/Heads/M_MED_HIS_Sparks_Head_01_ATH.M_MED_HIS_Sparks_Head_01_ATH",
        "SubPathString": ""
      },
      {
        "AssetPathName": "/BRCosmetics/Athena/Heroes/Meshes/Bodies/CP_026_Athena_Body.CP_026_Athena_Body",
        "SubPathString": ""
      },
      {
        "AssetPathName": "/BRCosmetics/Characters/CharacterParts/Hats/Hat_M_Commando_06.Hat_M_Commando_06",
        "SubPathString": ""
      }
    ],
    "Gender": "EFortCustomGender::Male",
    "DefaultMontageLookupTable": {
      "AssetPathName": "/Game/Animation/Game/MainPlayer/Menu/MontageLookUpTables/MediumMale.MediumMale",
      "SubPathString": ""
    },
    "ItemVariants": [
      {
        "ObjectName": "FortCosmeticPropertyVariant'CID_026_Athena_Commando_M:FortCosmeticPropertyVariant_0'",
        "ObjectPath": "/BRCosmetics/Athena/Items/Cosmetics/Characters/CID_026_Athena_Commando_M.1"
      }
    ],
    "ShotGridIds": [
      17958
    ],
    "BaseShotGridId": 17958,
    "Rarity": "EFortRarity::Rare",
    "ItemName": {
      "Namespace": "",
      "Key": "1B0FF5EC47AD35D5369AD092F4D8445B",
      "SourceString": "Desperado",
      "LocalizedString": "Desperado"
    },
    "ItemDescription": {
      "Namespace": "",
      "Key": "8222639D41F2A6189CEE0E92E5DE8B76",
      "SourceString": "Rare desperado outfit. ",
      "LocalizedString": "Rare desperado outfit. "
    },
    "ItemShortDescription": {
      "Namespace": "",
      "Key": "33E5371849B9B9B043BB76B86B828CC8",
      "SourceString": "Outfit",
      "LocalizedString": "Outfit"
    },
    "DataList": [
      {
        "LargeIcon": {
          "AssetPathName": "/BRCosmetics/UI/Foundation/Textures/Icons/Heroes/Athena/Soldier/T-Soldier-HID-026-Athena-Commando-M-L.T-Soldier-HID-026-Athena-Commando-M-L",
          "SubPathString": ""
        }
      },
      {
        "Icon": {
          "AssetPathName": "/BRCosmetics/UI/Foundation/Textures/Icons/Heroes/Athena/Soldier/T-Soldier-HID-026-Athena-Commando-M.T-Soldier-HID-026-Athena-Commando-M",
          "SubPathString": ""
        }
      },
      {
        "MinLevel": 1,
        "MaxLevel": 1
      },
      {
        "Tags": [
          "Cosmetics.Source.ItemShop",
          "Cosmetics.Filter.Season.1",
          "SoundLibrary.ID.StepType.BootsCombat",
          "SoundLibrary.ID.HandType.Glove",
          "SoundLibrary.ID.ClothingType.GearTactical",
          "Cosmetics.Gating.Allow.Shoes"
        ]
      },
      {
        "Traits": [
          "Item.Trait.SingleStack"
        ]
      },
      {
        "GeneratedTagsIndexes": [
          538,
          238,
          270,
          611,
          359,
          247,
          563,
          166,
          48,
          19,
          2743,
          178,
          690,
          16,
          796,
          835,
          1559,
          502,
          1116,
          186,
          1147,
          480,
          1218,
          1056,
          1058,
          1219,
          1299,
          1483,
          8049
        ]
      }
    ]
  }
}