{
  "Type": "AthenaDanceItemDefinition",
  "Name": "EID_WishingStar",
  "Class": "UScriptClass'AthenaDanceItemDefinition'",
  "Flags": "RF_Public | RF_Standalone | RF_Transactional | RF_WasLoaded | RF_LoadCompleted",
  "Properties": {
    "Animation": {
      "AssetPathName": "/BRCosmetics/Animation/Game/MainPlayer/Emotes/WishingStar/Emote_WishingStar_CMM_M.Emote_WishingStar_CMM_M",
      "SubPathString": ""
    },
    "AnimationFemaleOverride": {
      "AssetPathName": "/BRCosmetics/Animation/Game/MainPlayer/Emotes/WishingStar/CMF/Emote_WishingStar_CMF_M.Emote_WishingStar_CMF_M",
      "SubPathString": ""
    },
    "AnimationOverrides": [
      {
        "BodyType": "EFortCustomBodyType::Large",
        "Gender": "EFortCustomGender::Male",
        "EmoteMontage": {
          "AssetPathName": "/BRCosmetics/Animation/Game/MainPlayer/Emotes/WishingStar/CLM/Emote_WishingStar_CLM_M.Emote_WishingStar_CLM_M",
          "SubPathString": ""
        }
      },
      {
        "BodyType": "EFortCustomBodyType::Large",
        "Gender": "EFortCustomGender::Female",
        "EmoteMontage": {
          "AssetPathName": "/BRCosmetics/Animation/Game/MainPlayer/Emotes/WishingStar/CLF/Emote_WishingStar_CLF_M.Emote_WishingStar_CLF_M",
          "SubPathString": ""
        }
      }
    ],
    "EmoteCooldownSecs": 1.0,
    "ItemName": {
      "Namespace": "",
      "Key": "2B12781B46BD5D4F4ABBA082E54EA8FE",
      "SourceString": "Wishing Star",
      "LocalizedString": "Wishing Star"
    },
    "ItemDescription": {
      "Namespace": "",
      "Key": "DDC0FD624937291A174C28A085A8FCE5",
      "SourceString": "What did you wish for??",
      "LocalizedString": "What did you wish for??"
    },
    "ItemShortDescription": {
      "Namespace": "",
      "Key": "C5C01685440E184AA6D8898E2B3AE635",
      "SourceString": "Emote",
      "LocalizedString": "Emote"
    },
    "DataList": [
      {
        "MeshOverride": {
          "AssetPathName": "",
          "SubPathString": ""
        },
        "SkeletalMeshOverride": {
          "AssetPathName": "",
          "SubPathString": ""
        },
        "PivotOffset": {
          "X": 0.0,
          "Y": 155.0,
          "Z": 60.0
        },
        "InitialRotation": {
          "Pitch": 0.0,
          "Yaw": 0.0,
          "Roll": 0.0
        },
        "Scale": 1.0
      },
      {
        "Tags": [
          "Cosmetics.EmoteType.Dance",
          "Cosmetics.Source.ItemShop",
          "Cosmetics.Filter.Season.35"
        ]
      },
      {
        "Icon": {
          "AssetPathName": "/BRCosmetics/UI/Foundation/Textures/Icons/Emotes/S35/T_Icon_Emotes_WishingStar.T_Icon_Emotes_WishingStar",
          "SubPathString": ""
        }
      },
      {
        "LargeIcon": {
          "AssetPathName": "/BRCosmetics/UI/Foundation/Textures/Icons/Emotes/S35/T_Icon_Emotes_WishingStar_L.T_Icon_Emotes_WishingStar_L",
          "SubPathString": ""
        }
      },
      {
        "MinLevel": 1,
        "MaxLevel": 1
      },
      {
        "Traits": [
          "Item.Trait.SingleStack"
        ]
      }
    ]
  }
}