{
  "Type": "AthenaGliderItemDefinition",
  "Name": "Glider_ID_168_StreetRacerDriftRemix",
  "Class": "UScriptClass'AthenaGliderItemDefinition'",
  "Flags": "RF_Public | RF_Standalone | RF_Transactional | RF_WasLoaded | RF_LoadCompleted",
  "Properties": {
    "CameraFramingBoundsCenterOffset": {
      "X": 0.0,
      "Y": -15.0,
      "Z": -5.0
    },
    "ParachutePrefabClass": {
      "AssetPathName": "/BRCosmetics/Athena/Cosmetics/Blueprints/Gliders/LegacyGliderBPs/B_Athena_Glider_Legacy_StreetRacerDriftRemix.B_Athena_Glider_Legacy_StreetRacerDriftRemix_C",
      "SubPathString": ""
    },
    "SkeletalMesh": {
      "AssetPathName": "/BRCosmetics/Gadgets/Assets/VinderTech_GliderChute/Glider_Street_Racer_Drift_Remix/Meshes/Street_Racer_Drift_Remix_Glider.Street_Racer_Drift_Remix_Glider",
      "SubPathString": ""
    },
    "GliderMeshTransform": {
      "Rotation": {
        "X": 0.0,
        "Y": 0.0,
        "Z": 0.0,
        "W": 1.0,
        "IsNormalized": true,
        "Size": 1.0,
        "SizeSquared": 1.0
      },
      "Translation": {
        "X": 0.0,
        "Y": 0.0,
        "Z": 0.0
      },
      "Scale3D": {
        "X": 1.0,
        "Y": 1.0,
        "Z": 1.0
      }
    },
    "AnimClass": {
      "AssetPathName": "/BRCosmetics/Gadgets/Assets/VinderTech_GliderChute/Blueprints/Street_Racer_Drift_Remix_Glider_AnimBP.Street_Racer_Drift_Remix_Glider_AnimBP_C",
      "SubPathString": ""
    },
    "PlayerAnimSet": {
      "AssetPathName": "/Game/Animation/Game/MainPlayer/Skydive/ParaGlide/HangGlider/HangGliderPlayerAnimSet.HangGliderPlayerAnimSet",
      "SubPathString": ""
    },
    "OpenSound": {
      "AssetPathName": "/BRCosmetics/Sounds/Gliders/StreetRacerDrift/Glider_StreetRacerDrift_Open_Cue.Glider_StreetRacerDrift_Open_Cue",
      "SubPathString": ""
    },
    "CloseSound": {
      "AssetPathName": "/BRCosmetics/Sounds/Gliders/StreetRacerDrift/Glider_StreetRacerDrift_Close_Cue.Glider_StreetRacerDrift_Close_Cue",
      "SubPathString": ""
    },
    "TrailEffect": {
      "AssetPathName": "/BRCosmetics/Gadgets/Assets/VinderTech_GliderChute/Glider_Street_Racer_Drift_Remix/FX/P_Glider_DriftRemix_AnimTrail.P_Glider_DriftRemix_AnimTrail",
      "SubPathString": ""
    },
    "TrailEffect2": {
      "AssetPathName": "/BRCosmetics/Gadgets/Assets/VinderTech_GliderChute/Glider_Street_Racer_Drift_Remix/FX/P_Glider_DriftRemix_AnimTrail.P_Glider_DriftRemix_AnimTrail",
      "SubPathString": ""
    },
    "Rarity": "EFortRarity::Rare",
    "ItemName": {
      "Namespace": "",
      "Key": "9E33F70C4D59EF81AA0E3D958AAF4C57",
      "SourceString": "Rift Rider",
      "LocalizedString": "Rift Rider"
    },
    "ItemDescription": {
      "Namespace": "",
      "Key": "8564B7F04516C3FAAFC9DB96CF994592",
      "SourceString": "Cruise the dimensional highway.",
      "LocalizedString": "Cruise the dimensional highway."
    },
    "ItemShortDescription": {
      "Namespace": "",
      "Key": "F6696CF34A757AA818C004912AAFEC0F",
      "SourceString": "Glider",
      "LocalizedString": "Glider"
    },
    "DataList": [
      {
        "MeshOverride": {
          "AssetPathName": "",
          "SubPathString": ""
        },
        "SkeletalMeshOverride": {
          "AssetPathName": "",
          "SubPathString": ""
        },
        "PivotOffset": {
          "X": 0.0,
          "Y": 0.0,
          "Z": 0.0
        },
        "InitialRotation": {
          "Pitch": -15.0,
          "Yaw": -110.0,
          "Roll": -30.0
        },
        "Scale": 0.85
      },
      {
        "MinLevel": 1,
        "MaxLevel": 1
      },
      {
        "Icon": {
          "AssetPathName": "/BRCosmetics/UI/Foundation/Textures/Icons/Skydiving/T-Icon_Glider-StreetRacerDriftRemixGlider.T-Icon_Glider-StreetRacerDriftRemixGlider",
          "SubPathString": ""
        }
      },
      {
        "LargeIcon": {
          "AssetPathName": "/BRCosmetics/UI/Foundation/Textures/Icons/Skydiving/T-Icon_Glider-StreetRacerDriftRemixGlider-L.T-Icon_Glider-StreetRacerDriftRemixGlider-L",
          "SubPathString": ""
        }
      },
      {
        "Tags": [
          "Cosmetics.Set.Drift",
          "Cosmetics.Source.Season10.BattlePass.Paid",
          "Cosmetics.Filter.Season.10"
        ]
      },
      {
        "Traits": [
          "Item.Trait.SingleStack"
        ]
      },
      {
        "GeneratedTagsIndexes": [
          546,
          556,
          249,
          262,
          626,
          285,
          221,
          438,
          1062,
          1108,
          1795,
          116,
          1373,
          144,
          1874,
          2360,
          2362,
          1958,
          2845
        ]
      }
    ]
  }
}