{
  "Type": "AthenaLoadingScreenItemDefinition",
  "Name": "LSID_258_Backspin",
  "Class": "UScriptClass'AthenaLoadingScreenItemDefinition'",
  "Flags": "RF_Public | RF_Standalone | RF_Transactional | RF_WasLoaded | RF_LoadCompleted",
  "Properties": {
    "BackgroundImage": {
      "AssetPathName": "/BRCosmetics/2dAssets/Loadingscreens/Season14/Textures/T_LS_S14_Backspin.T_LS_S14_Backspin",
      "SubPathString": ""
    },
    "BackgroundColor": {
      "R": 0.008023,
      "G": 0.0,
      "B": 0.116971,
      "A": 1.0,
      "Hex": "160060"
    },
    "ItemName": {
      "Namespace": "",
      "Key": "C4229E9848D1B53E9AB95DAA2BD6DE74",
      "SourceString": "The Daywalker",
      "LocalizedString": "The Daywalker"
    },
    "ItemDescription": {
      "Namespace": "",
      "Key": "364098024F78812924F2878A251E32E6",
      "SourceString": "His Name Is... Blade!",
      "LocalizedString": "His Name Is... Blade!"
    },
    "ItemShortDescription": {
      "Namespace": "",
      "Key": "FF2E53BB4AEE0DEB7FD2B6AA62E9C037",
      "SourceString": "Loading Screen",
      "LocalizedString": "Loading Screen"
    },
    "DataList": [
      {
        "MinLevel": 1,
        "MaxLevel": 1
      },
      {
        "Traits": [
          "Item.Trait.SingleStack"
        ]
      },
      {
        "MeshOverride": {
          "AssetPathName": "",
          "SubPathString": ""
        },
        "SkeletalMeshOverride": {
          "AssetPathName": "",
          "SubPathString": ""
        },
        "PivotOffset": {
          "X": 20.0,
          "Y": -15.0,
          "Z": -30.654663
        },
        "InitialRotation": {
          "Pitch": -2.9999897,
          "Yaw": 74.99993,
          "Roll": 5.000015
        },
        "Scale": 3.0
      },
      {
        "Series": {
          "ObjectName": "FortItemSeriesDefinition'MarvelSeries'",
          "ObjectPath": "/BRCosmetics/Athena/Items/Cosmetics/Series/MarvelSeries.0"
        }
      },
      {
        "Icon": {
          "AssetPathName": "/BRCosmetics/2dAssets/Loadingscreens/Season14/PreviewImages/T_LS_S14_Blade_S.T_LS_S14_Blade_S",
          "SubPathString": ""
        }
      },
      {
        "LargeIcon": {
          "AssetPathName": "/BRCosmetics/2dAssets/Loadingscreens/Season14/PreviewImages/T_LS_S14_Blade_L.T_LS_S14_Blade_L",
          "SubPathString": ""
        }
      },
      {
        "Tags": [
          "Cosmetics.Filter.Season.14",
          "Cosmetics.Set.SweetMeaning"
        ]
      },
      {
        "GeneratedTagsIndexes": [
          490,
          238,
          541,
          546,
          231,
          247,
          114,
          248,
          579,
          262,
          244,
          389,
          24,
          635,
          674,
          193,
          568,
          32,
          757,
          1537,
          1647,
          2006,
          1858,
          3107,
          5184
        ]
      }
    ]
  }
}