{
  "Type": "AthenaPickaxeItemDefinition",
  "Name": "Pickaxe_MarbleShimmer_Keytar",
  "Class": "UScriptClass'AthenaPickaxeItemDefinition'",
  "Flags": "RF_Public | RF_Standalone | RF_Transactional | RF_WasLoaded | RF_LoadCompleted",
  "Properties": {
    "CameraFramingBounds": {
      "Origin": {
        "X": 0.0,
        "Y": -10.0,
        "Z": 25.0
      },
      "CylinderHalfHeight": 65.0,
      "CylinderRadius": 30.0
    },
    "WeaponDefinition": {
      "ObjectName": "FortWeaponMeleeDualWieldItemDefinition'Weapon_Pickaxe_MarbleShimmer_Keytar'",
      "ObjectPath": "/SparksCosmetics/Items/Weapons/Weapon_Pickaxe_MarbleShimmer_Keytar.0"
    },
    "ItemVariants": [
      {
        "ObjectName": "FortCosmeticParticleVariant'Pickaxe_MarbleShimmer_Keytar:FortCosmeticParticleVariant_0'",
        "ObjectPath": "/SparksCosmetics/Items/Cosmetics/Pickaxes/Pickaxe_MarbleShimmer_Keytar.1"
      }
    ],
    "ItemPreviewActorClass": {
      "AssetPathName": "/Game/Environments/FrontEnd/Blueprints/ItemPreview/ItemOnPawnPreview.ItemOnPawnPreview_C",
      "SubPathString": ""
    },
    "ShotGridIds": [
      63885
    ],
    "BaseShotGridId": 63885,
    "Rarity": "EFortRarity::Rare",
    "ItemName": {
      "Namespace": "",
      "Key": "17A436D044C7F3ACA28EA9B945C12341",
      "SourceString": "Keyluxe",
      "LocalizedString": "Keyluxe"
    },
    "ItemDescription": {
      "Namespace": "",
      "Key": "F7610AD94CFEAAB8C2D24F80F594360C",
      "SourceString": "Shimmer as you show off.",
      "LocalizedString": "Shimmer as you show off."
    },
    "ItemShortDescription": {
      "Namespace": "",
      "Key": "C843996B43246DD5284C95AECCD3D5BC",
      "SourceString": "Pickaxe",
      "LocalizedString": "Pickaxe"
    },
    "DataList": [
      {
        "MeshOverride": {
          "AssetPathName": "",
          "SubPathString": ""
        },
        "SkeletalMeshOverride": {
          "AssetPathName": "",
          "SubPathString": ""
        },
        "PivotOffset": {
          "X": -20.0,
          "Y": -15.0,
          "Z": -32.0
        },
        "InitialRotation": {
          "Pitch": -30.0,
          "Yaw": 90.0,
          "Roll": 0.0
        },
        "Scale": 1.0
      },
      {
        "MinLevel": 1,
        "MaxLevel": 1
      },
      {
        "Traits": [
          "Item.Trait.SingleStack"
        ]
      },
      {
        "Icon": {
          "AssetPathName": "/SparksCosmetics/UI/Icons/Keytar/S31/Icons/T_UI_Icon_Keytar_MarbleShimmer.T_UI_Icon_Keytar_MarbleShimmer",
          "SubPathString": ""
        }
      },
      {
        "LargeIcon": {
          "AssetPathName": "/SparksCosmetics/UI/Icons/Keytar/S31/Icons/T_UI_Icon_Keytar_MarbleShimmer_L.T_UI_Icon_Keytar_MarbleShimmer_L",
          "SubPathString": ""
        }
      },
      {
        "Tags": [
          "Cosmetics.Filter.Sparks.Season.05",
          "Cosmetics.Source.SparksPass",
          "UI.ItemPreview.Modifier.InstrumentPickaxe",
          "Cosmetics.Type.Pickaxe",
          "Cosmetics.UserFacingFlags.HasVariants",
          "Cosmetics.Pickaxe.OneHanded"
        ]
      },
      {
        "GeneratedTagsIndexes": [
          238,
          359,
          248,
          162,
          576,
          652,
          246,
          221,
          773,
          905,
          116,
          1180,
          437,
          1358,
          2306,
          800,
          436,
          2415,
          2621,
          3127,
          3128,
          6593
        ]
      }
    ]
  }
}