{
  "Type": "AthenaSkyDiveContrailItemDefinition",
  "Name": "Trails_ID_024_DieselSmoke",
  "Class": "UScriptClass'AthenaSkyDiveContrailItemDefinition'",
  "Flags": "RF_Public | RF_Standalone | RF_Transactional | RF_WasLoaded | RF_LoadCompleted",
  "Properties": {
    "ContrailEffect": {
      "AssetPathName": "/BRCosmetics/Athena/Effects/Particles/Skydiving/P_Contrail_DieselPunk.P_Contrail_DieselPunk",
      "SubPathString": ""
    },
    "PreviewPawnRotationOffset": {
      "Pitch": 0.0,
      "Yaw": -35.0,
      "Roll": 0.0
    },
    "Rarity": "EFortRarity::Rare",
    "ItemName": {
      "Namespace": "",
      "Key": "23A98BEC40B6218879FAC4AA1108CE99",
      "SourceString": "Exhaust",
      "LocalizedString": "Exhaust"
    },
    "ItemDescription": {
      "Namespace": "",
      "Key": "059E3D2E4C9623EEEFA11BA8D557C3B2",
      "SourceString": "Don't breathe in the fumes.",
      "LocalizedString": "Don't breathe in the fumes."
    },
    "ItemShortDescription": {
      "Namespace": "",
      "Key": "0BA7D35942A743C8DF87A1861EB46E38",
      "SourceString": "Contrail",
      "LocalizedString": "Contrail"
    },
    "DataList": [
      {
        "MinLevel": 1,
        "MaxLevel": 1
      },
      {
        "Traits": [
          "Item.Trait.SingleStack"
        ]
      },
      {
        "Tags": [
          "Cosmetics.Source.Season6.BattlePass.Paid",
          "Cosmetics.Set.DieselPunk",
          "Cosmetics.Filter.Season.6",
          "Cosmetics.BattlepassTrack.Display.DisableVFXDuringTransitionIn",
          "Cosmetics.BattlepassTrack.Display.DisableVFXDuringTransitionOut"
        ]
      },
      {
        "Icon": {
          "AssetPathName": "/BRCosmetics/UI/Foundation/Textures/Icons/Skydiving/FX-Trails/T-Icon-Trails-FX-DieselSmoke.T-Icon-Trails-FX-DieselSmoke",
          "SubPathString": ""
        }
      },
      {
        "LargeIcon": {
          "AssetPathName": "/BRCosmetics/UI/Foundation/Textures/Icons/Skydiving/FX-Trails/T-Icon-Trails-FX-DieselSmoke-L.T-Icon-Trails-FX-DieselSmoke-L",
          "SubPathString": ""
        }
      },
      {
        "MeshOverride": {
          "AssetPathName": "",
          "SubPathString": ""
        },
        "SkeletalMeshOverride": {
          "AssetPathName": "",
          "SubPathString": ""
        },
        "PivotOffset": {
          "X": 15.0,
          "Y": 120.0,
          "Z": 45.0
        },
        "InitialRotation": {
          "Pitch": 0.0,
          "Yaw": 0.0,
          "Roll": 0.0
        },
        "Scale": 1.0
      },
      {
        "GeneratedTagsIndexes": [
          238,
          546,
          359,
          162,
          576,
          564,
          276,
          1651,
          52,
          1042,
          89,
          1180,
          318,
          1506,
          1508,
          1700,
          304,
          385,
          398,
          2509,
          2510,
          3465
        ]
      }
    ]
  }
}