{
  "Type": "AthenaCharacterItemDefinition",
  "Name": "Bean_PumpkinSpice",
  "Class": "UScriptClass'AthenaCharacterItemDefinition'",
  "Flags": "RF_Public | RF_Standalone | RF_Transactional | RF_WasLoaded | RF_LoadCompleted",
  "Properties": {
    "BaseCharacterParts": [
      {
        "AssetPathName": "/BeanstalkCosmetics/Cosmetics/Head/CP_Bean_Head_Hood.CP_Bean_Head_Hood",
        "SubPathString": ""
      },
      {
        "AssetPathName": "/BeanstalkCosmetics/Cosmetics/Body/CP_Bean_Body_Fantasy.CP_Bean_Body_Fantasy",
        "SubPathString": ""
      }
    ],
    "Gender": "EFortCustomGender::Female",
    "AdditionalDataFields": [
      {
        "ObjectName": "BeanCosmeticItemDefinitionBase'Bean_PumpkinSpice:BeanCosmeticItemDefinitionBase_1'",
        "ObjectPath": "/BeanstalkCosmetics/Cosmetics/Def/CID/Bean_PumpkinSpice.1"
      }
    ],
    "ItemName": {
      "Namespace": "",
      "Key": "323BB67B4B819699E5AD8AA318D86425",
      "SourceString": "Patch",
      "LocalizedString": "Patch"
    },
    "ItemDescription": {
      "Namespace": "",
      "Key": "227296CE4703856DB2F5DF80A2303B8B",
      "SourceString": "Carve out your place in the night.",
      "LocalizedString": "Carve out your place in the night."
    },
    "ItemShortDescription": {
      "Namespace": "",
      "Key": "9658361F4EFF6B98FF153898E58C9D52",
      "SourceString": "Outfit",
      "LocalizedString": "Outfit"
    },
    "DataList": [
      {
        "Icon": {
          "AssetPathName": "/BeanstalkCosmetics/Cosmetics/Icons/T_Bean_PumpkinSpice.T_Bean_PumpkinSpice",
          "SubPathString": ""
        }
      },
      {
        "LargeIcon": {
          "AssetPathName": "/BeanstalkCosmetics/Cosmetics/Icons/T_Bean_PumpkinSpice_L.T_Bean_PumpkinSpice_L",
          "SubPathString": ""
        }
      },
      {
        "MinLevel": 1,
        "MaxLevel": 1
      },
      {
        "Tags": [
          "Beanstalk.Cosmetics.Character",
          "Cosmetics.Filter.Season.14",
          "Cosmetics.Set.PumpkinGang",
          "Phoebe.Cosmetic.Minus.Zone1"
        ]
      },
      {
        "Traits": [
          "Item.Trait.Transient",
          "Item.Trait.SingleStack"
        ]
      }
    ]
  }
}