{
  "Type": "AthenaDanceItemDefinition",
  "Name": "EID_Drum_RensDrums",
  "Class": "UScriptClass'AthenaDanceItemDefinition'",
  "Flags": "RF_Public | RF_Standalone | RF_Transactional | RF_WasLoaded | RF_LoadCompleted",
  "Properties": {
    "Animation": {
      "AssetPathName": "/SparksCosmetics/Emotes/Drum/RensDrums/Persistent/Emote_Drum_RensDrums_CMM_M.Emote_Drum_RensDrums_CMM_M",
      "SubPathString": ""
    },
    "AnimationFemaleOverride": {
      "AssetPathName": "/SparksCosmetics/Emotes/Drum/RensDrums/Persistent/Emote_Drum_RensDrums_CMF_M.Emote_Drum_RensDrums_CMF_M",
      "SubPathString": ""
    },
    "AnimationOverrides": [
      {
        "BodyType": "EFortCustomBodyType::Large",
        "Gender": "EFortCustomGender::Male",
        "EmoteMontage": {
          "AssetPathName": "/SparksCosmetics/Emotes/Drum/RensDrums/Persistent/Emote_Drum_RensDrums_CLM_M.Emote_Drum_RensDrums_CLM_M",
          "SubPathString": ""
        }
      },
      {
        "BodyType": "EFortCustomBodyType::Large",
        "Gender": "EFortCustomGender::Female",
        "EmoteMontage": {
          "AssetPathName": "/SparksCosmetics/Emotes/Drum/RensDrums/Persistent/Emote_Drum_RensDrums_CLF_M.Emote_Drum_RensDrums_CLF_M",
          "SubPathString": ""
        }
      }
    ],
    "EmoteCooldownSecs": 1.0,
    "bMontageContainsFacialAnimation": true,
    "ItemVariants": [
      {
        "ObjectName": "FortCosmeticProfileLoadoutVariant'EID_Drum_RensDrums:FortCosmeticProfileLoadoutVariant_0'",
        "ObjectPath": "/SparksCosmetics/Emotes/Drum/RensDrums/EID_Drum_RensDrums.1"
      }
    ],
    "Rarity": "EFortRarity::Common",
    "ItemName": {
      "Namespace": "",
      "Key": "3C080A3B4E26F271BD11AE85DACA6788",
      "SourceString": "Sticky Situation",
      "LocalizedString": "Sticky Situation"
    },
    "ItemDescription": {
      "Namespace": "",
      "Key": "240611E04A64CAE1FB2A8C85304B7C83",
      "SourceString": "Take that sticktoitiveness for a spin. ",
      "LocalizedString": "Take that sticktoitiveness for a spin. "
    },
    "ItemShortDescription": {
      "Namespace": "",
      "Key": "2AE84FBC46B76D76F80548BD3DC1CCF3",
      "SourceString": "Emote",
      "LocalizedString": "Emote"
    },
    "DataList": [
      {
        "MeshOverride": {
          "AssetPathName": "",
          "SubPathString": ""
        },
        "SkeletalMeshOverride": {
          "AssetPathName": "",
          "SubPathString": ""
        },
        "PivotOffset": {
          "X": 0.0,
          "Y": 0.0,
          "Z": 5.0
        },
        "InitialRotation": {
          "Pitch": 0.0,
          "Yaw": 0.0,
          "Roll": 0.0
        },
        "Scale": 0.55
      },
      {
        "Icon": {
          "AssetPathName": "/SparksCosmetics/UI/Icons/Emotes/S30/Icons/T-UI-Icon-SparksEmote-RensDrums.T-UI-Icon-SparksEmote-RensDrums",
          "SubPathString": ""
        }
      },
      {
        "LargeIcon": {
          "AssetPathName": "/SparksCosmetics/UI/Icons/Emotes/S30/Icons/T-UI-Icon-SparksEmote-RensDrums-L.T-UI-Icon-SparksEmote-RensDrums-L",
          "SubPathString": ""
        }
      },
      {
        "MinLevel": 1,
        "MaxLevel": 1
      },
      {
        "Tags": [
          "Cosmetics.EmoteType.Dance",
          "Cosmetics.Filter.Sparks",
          "ChallengeBundle.Source.Season30",
          "Cosmetics.Emote.HideMimosaInPreview"
        ]
      },
      {
        "Traits": [
          "Item.Trait.SingleStack"
        ]
      }
    ]
  }
}