{
  "Type": "AthenaDanceItemDefinition",
  "Name": "EID_MiddleSock",
  "Class": "UScriptClass'AthenaDanceItemDefinition'",
  "Flags": "RF_Public | RF_Standalone | RF_Transactional | RF_WasLoaded | RF_LoadCompleted",
  "Properties": {
    "StaticToTraversalBlendTime": 0.4,
    "TraversalToStaticBlendTime": 0.4,
    "FrontEndAnimation": {
      "AssetPathName": "/BRCosmetics/Animation/Game/MainPlayer/Emotes/MiddleSock/CMM/Emote_MiddleSock_CMM_M_Frontend.Emote_MiddleSock_CMM_M_Frontend",
      "SubPathString": ""
    },
    "FrontEndAnimationFemaleOverride": {
      "AssetPathName": "/BRCosmetics/Animation/Game/MainPlayer/Emotes/MiddleSock/CMF/Emote_MiddleSock_CMF_M_Frontend.Emote_MiddleSock_CMF_M_Frontend",
      "SubPathString": ""
    },
    "FrontEndAnimationOverrides": [
      {
        "BodyType": "EFortCustomBodyType::Large",
        "Gender": "EFortCustomGender::Male",
        "EmoteMontage": {
          "AssetPathName": "/BRCosmetics/Animation/Game/MainPlayer/Emotes/MiddleSock/CLM/Emote_MiddleSock_CLM_M_Frontend.Emote_MiddleSock_CLM_M_Frontend",
          "SubPathString": ""
        }
      },
      {
        "BodyType": "EFortCustomBodyType::Large",
        "Gender": "EFortCustomGender::Female",
        "EmoteMontage": {
          "AssetPathName": "/BRCosmetics/Animation/Game/MainPlayer/Emotes/MiddleSock/CLF/Emote_MiddleSock_CLF_M_Frontend.Emote_MiddleSock_CLF_M_Frontend",
          "SubPathString": ""
        }
      }
    ],
    "bMovingEmote": true,
    "WalkForwardSpeed": 139.0,
    "bMoveForwardOnly": true,
    "Animation": {
      "AssetPathName": "/BRCosmetics/Animation/Game/MainPlayer/Emotes/MiddleSock/CMM/Emote_MiddleSock_CMM_M.Emote_MiddleSock_CMM_M",
      "SubPathString": ""
    },
    "AnimationFemaleOverride": {
      "AssetPathName": "/BRCosmetics/Animation/Game/MainPlayer/Emotes/MiddleSock/CMF/Emote_MiddleSock_CMF_M.Emote_MiddleSock_CMF_M",
      "SubPathString": ""
    },
    "AnimationOverrides": [
      {
        "BodyType": "EFortCustomBodyType::Large",
        "Gender": "EFortCustomGender::Male",
        "EmoteMontage": {
          "AssetPathName": "/BRCosmetics/Animation/Game/MainPlayer/Emotes/MiddleSock/CLM/Emote_MiddleSock_CLM_M.Emote_MiddleSock_CLM_M",
          "SubPathString": ""
        }
      },
      {
        "BodyType": "EFortCustomBodyType::Large",
        "Gender": "EFortCustomGender::Female",
        "EmoteMontage": {
          "AssetPathName": "/BRCosmetics/Animation/Game/MainPlayer/Emotes/MiddleSock/CLF/Emote_MiddleSock_CLF_M.Emote_MiddleSock_CLF_M",
          "SubPathString": ""
        }
      }
    ],
    "EmoteCooldownSecs": 1.0,
    "ItemName": {
      "Namespace": "",
      "Key": "B3288C304EE2135F769BE18380522248",
      "SourceString": "Spider Stroll",
      "LocalizedString": "Spider Stroll"
    },
    "ItemDescription": {
      "Namespace": "",
      "Key": "7970B3D24F8C7B5628D585AA525403B2",
      "SourceString": "Stretch your legs... the 4 large iron ones.",
      "LocalizedString": "Stretch your legs... the 4 large iron ones."
    },
    "ItemShortDescription": {
      "Namespace": "",
      "Key": "8EAB0A2E4E57B3980D624BB36775AB40",
      "SourceString": "Emote",
      "LocalizedString": "Emote"
    },
    "DataList": [
      {
        "MeshOverride": {
          "AssetPathName": "",
          "SubPathString": ""
        },
        "SkeletalMeshOverride": {
          "AssetPathName": "",
          "SubPathString": ""
        },
        "PivotOffset": {
          "X": 0.0,
          "Y": 80.0,
          "Z": 25.0
        },
        "InitialRotation": {
          "Pitch": 0.0,
          "Yaw": 0.0,
          "Roll": 0.0
        },
        "Scale": 1.0
      },
      {
        "Icon": {
          "AssetPathName": "/BRCosmetics/UI/Foundation/Textures/Icons/Emotes/S31/TIconEmotesMiddleSock.TIconEmotesMiddleSock",
          "SubPathString": ""
        }
      },
      {
        "LargeIcon": {
          "AssetPathName": "/BRCosmetics/UI/Foundation/Textures/Icons/Emotes/S31/TIconEmotesMiddleSockL.TIconEmotesMiddleSockL",
          "SubPathString": ""
        }
      },
      {
        "Tags": [
          "Cosmetics.EmoteType.Dance",
          "Cosmetics.Source.ItemShop",
          "Cosmetics.Filter.Season.31",
          "Cosmetics.Set.BeardMosaic",
          "Cosmetics.UserFacingFlags.Emote.Traversal",
          "Cosmetics.Emote.HideMimosaInPreview",
          "Cosmetics.Emote.HideMimosaInPreview"
        ]
      },
      {
        "MinLevel": 1,
        "MaxLevel": 1
      },
      {
        "Traits": [
          "Item.Trait.SingleStack"
        ]
      },
      {
        "Series": {
          "ObjectName": "FortItemSeriesDefinition'MarvelSeries'",
          "ObjectPath": "/BRCosmetics/Athena/Items/Cosmetics/Series/MarvelSeries.0"
        }
      }
    ]
  }
}