{
  "Type": "AthenaLoadingScreenItemDefinition",
  "Name": "LSID_093_S7Cumulative10",
  "Class": "UScriptClass'AthenaLoadingScreenItemDefinition'",
  "Flags": "RF_Public | RF_Standalone | RF_Transactional | RF_WasLoaded | RF_LoadCompleted",
  "Properties": {
    "BackgroundImage": {
      "AssetPathName": "/BRCosmetics/2dAssets/Loadingscreens/Season7/T_LS_S7_Cumulative_10.T_LS_S7_Cumulative_10",
      "SubPathString": ""
    },
    "ItemName": {
      "Namespace": "",
      "Key": "566B107345CDB933F4E66C969B41FBAE",
      "SourceString": "Respite",
      "LocalizedString": "Respite"
    },
    "ItemDescription": {
      "Namespace": "",
      "Key": "DA379D444B9CF8AFD7AAD5BEABA2BF34",
      "SourceString": "Reinvigorated by the warmth of the flame.",
      "LocalizedString": "Reinvigorated by the warmth of the flame."
    },
    "ItemShortDescription": {
      "Namespace": "",
      "Key": "9D711F2F4A302568FC05348239590959",
      "SourceString": "Loading Screen",
      "LocalizedString": "Loading Screen"
    },
    "DataList": [
      {
        "MinLevel": 1,
        "MaxLevel": 1
      },
      {
        "Traits": [
          "Item.Trait.SingleStack"
        ]
      },
      {
        "Icon": {
          "AssetPathName": "/BRCosmetics/2dAssets/Loadingscreens/Season7/PreviewImages/S7-M-LS-10-S.S7-M-LS-10-S",
          "SubPathString": ""
        }
      },
      {
        "LargeIcon": {
          "AssetPathName": "/BRCosmetics/2dAssets/Loadingscreens/Season7/PreviewImages/S7-M-LS-10-L.S7-M-LS-10-L",
          "SubPathString": ""
        }
      },
      {
        "Tags": [
          "Cosmetics.Source.Season7.BattlePass.Paid",
          "Cosmetics.Set.S7Cumulative",
          "Cosmetics.Filter.Season.7"
        ]
      },
      {
        "MeshOverride": {
          "AssetPathName": "",
          "SubPathString": ""
        },
        "SkeletalMeshOverride": {
          "AssetPathName": "",
          "SubPathString": ""
        },
        "PivotOffset": {
          "X": 20.0,
          "Y": -15.0,
          "Z": -30.654663
        },
        "InitialRotation": {
          "Pitch": -2.9999897,
          "Yaw": 74.99993,
          "Roll": 5.000015
        },
        "Scale": 3.0
      },
      {
        "GeneratedTagsIndexes": [
          238,
          246,
          823,
          948,
          697,
          91,
          1042,
          1250,
          699,
          664,
          1428,
          1482,
          1483,
          1771,
          2467,
          2682,
          2683,
          2684,
          2685,
          5080
        ]
      }
    ]
  }
}