{
  "Type": "AthenaGliderItemDefinition",
  "Name": "Umbrella_Season_24",
  "Class": "UScriptClass'AthenaGliderItemDefinition'",
  "Flags": "RF_Public | RF_Standalone | RF_Transactional | RF_WasLoaded | RF_LoadCompleted",
  "Properties": {
    "GliderType": "EFortGliderType::Umbrella",
    "CameraFramingBoundsCenterOffset": {
      "X": -120.0,
      "Y": -10.0,
      "Z": 10.0
    },
    "ParachutePrefabClass": {
      "AssetPathName": "/Game/Athena/Cosmetics/Blueprints/B_Athena_Glider_Generic.B_Athena_Glider_Generic_C",
      "SubPathString": ""
    },
    "SkeletalMesh": {
      "AssetPathName": "/BRCosmetics/Gadgets/Assets/VinderTech_Umbrella/Umbrella_Season24/Meshes/Season_24_Glider.Season_24_Glider",
      "SubPathString": ""
    },
    "GliderMeshTransform": {
      "Rotation": {
        "X": 0.0,
        "Y": 0.0,
        "Z": 0.0,
        "W": 1.0,
        "IsNormalized": true,
        "Size": 1.0,
        "SizeSquared": 1.0
      },
      "Translation": {
        "X": 0.0,
        "Y": 0.0,
        "Z": 0.0
      },
      "Scale3D": {
        "X": 1.0,
        "Y": 1.0,
        "Z": 1.0
      }
    },
    "AnimClass": {
      "AssetPathName": "/BRCosmetics/Gadgets/Assets/VinderTech_Umbrella/VinderTech_Umbrella_AnimBP.VinderTech_Umbrella_AnimBP_C",
      "SubPathString": ""
    },
    "PlayerAnimSet": {
      "AssetPathName": "/Game/Animation/Game/MainPlayer/Skydive/ParaGlide/Umbrella/UmbrellaPlayerAnimSet.UmbrellaPlayerAnimSet",
      "SubPathString": ""
    },
    "TrailEffectDefinitions": [
      {
        "NiagaraSystem": {
          "AssetPathName": "/BRCosmetics/Gadgets/Assets/VinderTech_Umbrella/Umbrella_Season24/FX/NS_Umbrella_Season24.NS_Umbrella_Season24",
          "SubPathString": ""
        },
        "EffectSocket": "Melee_TwoHanded_Handle",
        "Offset": {
          "Rotation": {
            "X": 0.0,
            "Y": 0.0,
            "Z": 0.0,
            "W": 1.0,
            "IsNormalized": true,
            "Size": 1.0,
            "SizeSquared": 1.0
          },
          "Translation": {
            "X": 0.0,
            "Y": 0.0,
            "Z": 0.0
          },
          "Scale3D": {
            "X": 1.0,
            "Y": 1.0,
            "Z": 1.0
          }
        },
        "ActivationMode": "EGliderTrailActivationMode::AutoActivate",
        "AttachmentMode": "EGliderTrailAttachmentMode::GliderMesh"
      }
    ],
    "OpenSound": {
      "AssetPathName": "/BRCosmetics/Sounds/Gliders/Season24_Umbrella/SC_GliderOpen_S24Umbrella.SC_GliderOpen_S24Umbrella",
      "SubPathString": ""
    },
    "CloseSound": {
      "AssetPathName": "/BRCosmetics/Sounds/Gliders/Season24_Umbrella/SC_GliderClose_S24Umbrella.SC_GliderClose_S24Umbrella",
      "SubPathString": ""
    },
    "ThrustLoopSound": {
      "AssetPathName": "/BRCosmetics/Sounds/Gliders/Season24_Umbrella/GliderThrustLoop_S24Umbrella_Cue.GliderThrustLoop_S24Umbrella_Cue",
      "SubPathString": ""
    },
    "ThrustSoundParams": [
      {
        "Key": "ELayeredAudioTriggerDirection::Forwards",
        "Value": {
          "InterpType": "ELayeredAudioInterpolationType::Linear",
          "Curve": null,
          "AttackSpeed": 3.0,
          "ReleaseSpeed": 2.0,
          "Oneshots": [
            {
              "SoundRef": {
                "AssetPathName": "/BRCosmetics/Sounds/Gliders/Season24_Umbrella/SC_GliderThrustFwd_S24Umbrella.SC_GliderThrustFwd_S24Umbrella",
                "SubPathString": ""
              },
              "GateValue": 0.5,
              "Direction": "ELayeredAudioTriggerDir::Forward",
              "FadeWhenOutsideGate": true,
              "MinTimeSinceTrigger": 0.1,
              "InterruptFadeTime": 0.5
            }
          ]
        }
      },
      {
        "Key": "ELayeredAudioTriggerDirection::Sideways",
        "Value": {
          "InterpType": "ELayeredAudioInterpolationType::Linear",
          "Curve": null,
          "AttackSpeed": 3.0,
          "ReleaseSpeed": 2.0,
          "Oneshots": [
            {
              "SoundRef": {
                "AssetPathName": "/BRCosmetics/Sounds/Gliders/Season24_Umbrella/SC_GliderThrust_S24Umbrella.SC_GliderThrust_S24Umbrella",
                "SubPathString": ""
              },
              "GateValue": 0.5,
              "Direction": "ELayeredAudioTriggerDir::Forward",
              "FadeWhenOutsideGate": true,
              "MinTimeSinceTrigger": 0.1,
              "InterruptFadeTime": 0.5
            }
          ]
        }
      },
      {
        "Key": "ELayeredAudioTriggerDirection::Backwards",
        "Value": {
          "InterpType": "ELayeredAudioInterpolationType::Linear",
          "Curve": null,
          "AttackSpeed": 3.0,
          "ReleaseSpeed": 2.0,
          "Oneshots": [
            {
              "SoundRef": {
                "AssetPathName": "/BRCosmetics/Sounds/Gliders/Season24_Umbrella/SC_GliderThrustBkwd_S24Umbrella.SC_GliderThrustBkwd_S24Umbrella",
                "SubPathString": ""
              },
              "GateValue": 0.5,
              "Direction": "ELayeredAudioTriggerDir::Forward",
              "FadeWhenOutsideGate": true,
              "MinTimeSinceTrigger": 0.1,
              "InterruptFadeTime": 0.5
            }
          ]
        }
      }
    ],
    "ShotGridIds": [
      67568
    ],
    "ItemSearchTags": [
      {
        "Namespace": "",
        "Key": "08BA6847432A03D6970E2C8291E9FCF8",
        "SourceString": "Umbrella",
        "LocalizedString": "Umbrella"
      }
    ],
    "BaseShotGridId": 67568,
    "Rarity": "EFortRarity::Common",
    "ItemName": {
      "Namespace": "",
      "Key": "350B518B4F74E1127E2AFB8146825629",
      "SourceString": "MEGA-brella",
      "LocalizedString": "MEGA-brella"
    },
    "ItemDescription": {
      "Namespace": "",
      "Key": "EB2058E041E45C0F205A2BB7D5D8DE55",
      "SourceString": "Earned on the mean streets of the big city.",
      "LocalizedString": "Earned on the mean streets of the big city."
    },
    "ItemShortDescription": {
      "Namespace": "",
      "Key": "5110886B4B82702C760EDCBF12AFD624",
      "SourceString": "Glider",
      "LocalizedString": "Glider"
    },
    "DataList": [
      {
        "MeshOverride": {
          "AssetPathName": "",
          "SubPathString": ""
        },
        "SkeletalMeshOverride": {
          "AssetPathName": "",
          "SubPathString": ""
        },
        "PivotOffset": {
          "X": 0.0,
          "Y": 0.0,
          "Z": 0.0
        },
        "InitialRotation": {
          "Pitch": 15.0,
          "Yaw": 45.0,
          "Roll": 0.0
        },
        "Scale": 1.05
      },
      {
        "MinLevel": 1,
        "MaxLevel": 1
      },
      {
        "Icon": {
          "AssetPathName": "/BRCosmetics/UI/Foundation/Textures/Icons/Skydiving/S24/T-Icon_Glider-Umbrella-Season24.T-Icon_Glider-Umbrella-Season24",
          "SubPathString": ""
        }
      },
      {
        "LargeIcon": {
          "AssetPathName": "/BRCosmetics/UI/Foundation/Textures/Icons/Skydiving/S24/T-Icon_Glider-Umbrella-Season24-L.T-Icon_Glider-Umbrella-Season24-L",
          "SubPathString": ""
        }
      },
      {
        "Tags": [
          "Cosmetics.Filter.Season.24",
          "Cosmetics.QuestsMetaData.Achievements.Umbrella",
          "Cosmetics.Source.Season24.FirstWin"
        ]
      },
      {
        "Traits": [
          "Item.Trait.SingleStack"
        ]
      },
      {
        "GeneratedTagsIndexes": [
          238,
          546,
          248,
          569,
          105,
          593,
          262,
          607,
          591,
          667,
          592,
          585,
          854,
          438,
          1062,
          581,
          1115,
          217,
          2946,
          394,
          349
        ]
      }
    ]
  }
}